easyFace/__init__.py
easyFace/facedetectcnn.py
easyFace/libfacedetection_32bit.dll
easyFace/libfacedetection_32bit.so
easyFace/libfacedetection_64bit.dll
easyFace/libfacedetection_64bit.so
easyFace/libfacedetection_raspbian.so
easyFace-0.2.0.dist-info/METADATA
easyFace-0.2.0.dist-info/WHEEL
easyFace-0.2.0.dist-info/top_level.txt
easyFace-0.2.0.dist-info/RECORD
