Metadata-Version: 2.1
Name: easyFace
Version: 0.2.0
Summary: fork自zxxml的PyFace项目，增加了对32bit raspbian-buster系统的支持。底层使用了yushiqi开源的libfacedetection。具体使用方法见github
Home-page: https://github.com/zjuxumang/PyFace
Author: zhuzhuangtian
Author-email: 576583342@qq.com
License: UNKNOWN
Platform: all
Requires-Python: >=3.7
Requires-Dist: numpy
Requires-Dist: Pillow
Requires-Dist: opencv-python
